{"Exif":{"Lat":0,"Long":0,"Date":"2024-03-02T17:24:25-08:00","Tags":{"ApertureValue":1.69,"BitsPerSample":[8,8,8],"BrightnessValue":1.74,"DateTimeDigitized|time.Time":"2024-03-02T17:24:25-08:00","DateTimeOriginal|time.Time":"2024-03-02T17:24:25-08:00","DateTime|time.Time":"2024-03-02T17:43:03-08:00","DigitalZoomRatio":2.28,"ExposureTime|*big.Rat":"1/50","FNumber":1.8,"FocalLength":5.4,"FocalLengthIn35mmFilm|int":"23","ISOSpeedRatings|int":"160","ImageLength|int":"3000","ImageUniqueID":"M50QLPL00VM","ImageWidth|int":"4000","Make":"samsung","MaxApertureValue":1.69,"Model":"SM-W9024","Orientation|int":"1","PhotometricInterpretation|int":"2","PixelXDimension|int":"2856","PixelYDimension|int":"3640","SamplesPerPixel|int":"3","SceneCaptureType|int":"0","ShutterSpeedValue|*big.Rat":"1/50","Software":"Adobe Photoshop 23.4 (Windows)","SubSecTime":"231","SubSecTimeDigitized":"231","SubSecTimeOriginal":"231","YCbCrPositioning|int":"1"}}}
